{"cameraMode":{"drawMode":0,"name":"Shaded","section":"Shading Mode"},"sceneLighting":false,"audioPlay":false,"sceneViewState":{"m_AlwaysRefresh":false,"showFog":true,"showSkybox":false,"showFlares":true,"showImageEffects":true,"showParticleSystems":true,"showVisualEffectGraphs":true,"m_FxEnabled":true},"in2DMode":false,"pivot":{"x":1.4171968698501588,"y":0.1504809856414795,"z":1.923850178718567},"rotation":{"x":0.08805225789546967,"y":-0.03255756199359894,"z":0.002835693769156933,"w":0.9956271648406982},"size":1.900770902633667,"orthographic":false}